vrequest/__init__.py
vrequest/ast_hook_inject.js
vrequest/astjs.zip
vrequest/combinekey.py
vrequest/frame.py
vrequest/ico.ico
vrequest/main.js
vrequest/main.py
vrequest/menu.py
vrequest/py_my_scrapy_redis_server.py
vrequest/py_vthread.py
vrequest/pyaes.py
vrequest/pyascii_deviation.py
vrequest/pybacon.py
vrequest/pybase.py
vrequest/pyblowfish.py
vrequest/pybrainfuck.py
vrequest/pycaesar.py
vrequest/pycompress.py
vrequest/pycv2.py
vrequest/pydes.py
vrequest/pyevpkdf.py
vrequest/pyfinddesktopfile.py
vrequest/pygif.py
vrequest/pyjsdefusion.py
vrequest/pyjsfuck.py
vrequest/pyjspack.py
vrequest/pymapmd5.py
vrequest/pymd2.py
vrequest/pymini_yolo.py
vrequest/pymorse.py
vrequest/pymultialgo.py
vrequest/pyplus.py
vrequest/pypng2gif.py
vrequest/pyprime.py
vrequest/pypyzbar.py
vrequest/pyqrcode.py
vrequest/pyrail_fence.py
vrequest/pyrc4.py
vrequest/pyrots.py
vrequest/pyscreenshot.py
vrequest/pyserpent.py
vrequest/pyset_pypi_src.py
vrequest/pysimplejs2python.py
vrequest/pytwofish.py
vrequest/pywiener_attack.py
vrequest/pywindowproxy.py
vrequest/pyzlibaes.py
vrequest/root.py
vrequest/tab.py
vrequest/util.py
vrequest/template/scrapy.cfg
vrequest/template/v/__init__.py
vrequest/template/v/items.py
vrequest/template/v/middlewares.py
vrequest/template/v/pipelines.py
vrequest/template/v/settings.py
vrequest/template/v/spiders/__init__.py
vrequest-1.9.15.dist-info/LICENSE
vrequest-1.9.15.dist-info/METADATA
vrequest-1.9.15.dist-info/WHEEL
vrequest-1.9.15.dist-info/entry_points.txt
vrequest-1.9.15.dist-info/top_level.txt
vrequest-1.9.15.dist-info/RECORD
